README.md
setup.py
fmp_x.egg-info/PKG-INFO
fmp_x.egg-info/SOURCES.txt
fmp_x.egg-info/dependency_links.txt
fmp_x.egg-info/requires.txt
fmp_x.egg-info/top_level.txt
fmpx/__init__.py
fmpx/client.py