Metadata-Version: 2.1
Name: fmp-x
Version: 0.1.7.5
Summary: fmp quant client
Author: Ron Stark
